{
	"phase": 11,
	"tasks": [
		{
			"id": "p11-9",
			"title": "Metrics: record preview generation time, cache hit rate",
			"status": "Completed",
			"acceptanceCriteria": true
		},
		{
			"id": "p11-11",
			"title": "Cleanup daemon: periodic sweep and on-exit cleanup",
			"status": "Completed",
			"acceptanceCriteria": true
		},
		{
			"id": "p11-0",
			"title": "Phase planning document created and aligned with roadmap",
			"status": "Completed",
			"acceptanceCriteria": false
		},
		{
			"id": "p11-2",
			"title": "Implement TempPreviewService with disk cache + TTL cleanup",
			"status": "Completed",
			"acceptanceCriteria": false
		},
		{
			"id": "p11-3",
			"title": "Wire duplicate compare UI to prefer temp previews when needed",
			"status": "Completed",
			"acceptanceCriteria": false
		},
		{
			"id": "p11-4",
			"title": "Make Visual Compare the default view for duplicate groups",
			"status": "Completed",
			"acceptanceCriteria": false
		},
		{
			"id": "p11-7",
			"title": "Implement temp preview invalidation on source mtime/hash change",
			"status": "Completed",
			"acceptanceCriteria": false
		},
		{
			"id": "p11-10",
			"title": "Tests: RAW/HEIC preview generation and UI integration",
			"status": "Completed",
			"acceptanceCriteria": false
		},
		{
			"id": "p11-5",
			"title": "Add zoom/pan and side-by-side swap controls with keyboard shortcuts",
			"status": "Completed",
			"acceptanceCriteria": false
		},
		{
			"id": "p11-8",
			"title": "Settings: toggle for temp preview generation and max cache size",
			"status": "Completed",
			"acceptanceCriteria": false
		},
		{
			"id": "p11-12",
			"title": "Docs: brief user help for Visual Compare defaults and temp previews",
			"status": "Completed",
			"acceptanceCriteria": false
		},
		{
			"id": "p11-13",
			"title": "Temp previews: produce browser-valid WEBP for HEIC/RAW",
			"status": "Completed",
			"acceptanceCriteria": false
		},
		{
			"id": "p11-14",
			"title": "CompareView UX: img onerror fallback; better handling for video",
			"status": "Completed",
			"acceptanceCriteria": false
		},
		{
			"id": "p11-15",
			"title": "Duplicates list UI: constrain overflow/ellipsis for long paths",
			"status": "Completed",
			"acceptanceCriteria": false
		},
		{
			"id": "p11-16",
			"title": "Preview API for non-images/video: correct content-type + PNG fallback",
			"status": "Completed",
			"acceptanceCriteria": false
		}
	],
	"counts": {
		"total": 15,
		"completed": 15,
		"active": 0
	}
}
